[
  {
    "code": "BP-2t1e9j5b",
    "gender": "Polygender",
    "date_birth": "1989-02-01",
    "profession": "Environmental Tech",
    "fav_color": "Red",
    "scores": [
      1.54,
      3.49,
      4.9
    ]
  },
  {
    "code": "GJ-9y9h9w8l",
    "gender": "Female",
    "date_birth": "1959-05-02",
    "profession": "Quality Control Specialist",
    "fav_color": "Blue",
    "scores": [
      3.21,
      0.28,
      0.92
    ]
  },
  {
    "code": "HF-4y5k6a8a",
    "gender": "Male",
    "date_birth": "1961-01-22",
    "profession": "Quality Control Specialist",
    "fav_color": "Red",
    "scores": [
      3.96,
      0.67,
      2.11
    ]
  },
  {
    "code": "WU-1e3d7w7j",
    "gender": "Female",
    "date_birth": "2002-10-28",
    "profession": "Marketing Manager",
    "fav_color": "Blue",
    "scores": [
      3.02,
      4.54,
      4.77
    ]
  },
  {
    "code": "DM-6g3w0e4z",
    "gender": "Male",
    "date_birth": "1974-05-11",
    "profession": "Staff Scientist",
    "fav_color": "Blue",
    "scores": [
      3.31,
      1.32,
      2.72
    ]
  },
  {
    "code": "DT-9i2x6z1p",
    "gender": "Female",
    "date_birth": "1985-12-25",
    "profession": "Quality Engineer",
    "fav_color": "White",
    "scores": [
      3.18
    ]
  },
  {
    "code": "GE-1l4f5j7h",
    "gender": "Male",
    "date_birth": "1977-05-11",
    "profession": "Senior Financial Analyst",
    "fav_color": "Red",
    "scores": [
      0.68,
      3.97,
      3.85
    ]
  },
  {
    "code": "JU-exs9ol70",
    "gender": "Male",
    "date_birth": "1984-07-23",
    "profession": "Sales Associate",
    "fav_color": "White",
    "scores": [
      0.4,
      2.47,
      0.19
    ]
  },
  {
    "code": "BU-4x8n2b1t",
    "gender": "Genderfluid",
    "date_birth": "1969-04-13",
    "profession": "General Manager",
    "fav_color": "White",
    "scores": [
      1.57,
      4.54,
      2.14
    ]
  },
  {
    "code": "NF-3w7c5n3x",
    "gender": "Male",
    "date_birth": "1975-03-08",
    "profession": "Account Executive",
    "fav_color": "Blue",
    "scores": [
      0.91,
      1.23,
      3.09
    ]
  },
  {
    "code": "TR-9z3v5h8a",
    "gender": "Male",
    "date_birth": "1983-10-22",
    "profession": "Budget/Accounting Analyst I",
    "fav_color": "White",
    "scores": [
      4.54,
      0.34,
      1.41
    ]
  },
  {
    "code": "DV-u1b9bnr3",
    "gender": "Male",
    "date_birth": "1999-12-13",
    "profession": "Systems Administrator I",
    "fav_color": "Red",
    "scores": [
      1.35,
      3.3,
      4.41
    ]
  },
  {
    "code": "WY-1u0g7e3t",
    "gender": "Male",
    "date_birth": "1965-06-26",
    "profession": "Internal Auditor",
    "fav_color": "White",
    "scores": [
      2.66,
      2.06,
      1.82
    ]
  },
  {
    "code": "SA-8a6q0h7e",
    "gender": "Female",
    "date_birth": "1977-12-07",
    "profession": "Social Worker",
    "fav_color": "Blue",
    "scores": [
      4.99,
      2.76,
      3.52
    ]
  },
  {
    "code": "AF-1p3e1y0p",
    "gender": "Male",
    "date_birth": "1987-12-07",
    "profession": "Tax Accountant",
    "fav_color": "Blue",
    "scores": [
      0.75,
      1.68,
      3.56
    ]
  },
  {
    "code": "LB-7u8k3w1k",
    "gender": "Female",
    "date_birth": "1995-01-08",
    "profession": "Design Engineer",
    "fav_color": "White",
    "scores": [
      4.62,
      1.48,
      1.98
    ]
  },
  {
    "code": "GT-3p1k9u3x",
    "gender": "Female",
    "date_birth": "1963-12-11",
    "profession": "Structural Engineer",
    "fav_color": "Blue",
    "scores": [
      0.35,
      2.18,
      3.85
    ]
  },
  {
    "code": "HS-3q1i9o1g",
    "gender": "Male",
    "date_birth": "1960-02-17",
    "profession": "Geological Engineer",
    "fav_color": "Red",
    "scores": [
      0.69,
      3.98,
      2.73
    ]
  },
  {
    "code": "HD-8t6b6n1w",
    "gender": "Female",
    "date_birth": "1963-10-12",
    "profession": "Desktop Support Technician",
    "fav_color": "Blue",
    "scores": [
      1.6,
      3.01,
      4.0
    ]
  },
  {
    "code": "WD-udon3qos",
    "gender": "Male",
    "date_birth": "1990-02-05",
    "profession": "Editor",
    "fav_color": "Blue",
    "scores": [
      2.69,
      0.99,
      4.34
    ]
  },
  {
    "code": "OY-7t4q0g0v",
    "gender": "Male",
    "date_birth": "1974-09-21",
    "profession": "Food Chemist",
    "fav_color": "Red",
    "scores": [
      1.61,
      4.7,
      2.67
    ]
  },
  {
    "code": "LW-8k3p8a9n",
    "gender": "Female",
    "date_birth": "1975-04-16",
    "profession": "Product Engineer",
    "fav_color": "White",
    "scores": [
      2.83,
      4.87,
      3.3
    ]
  },
  {
    "code": "ZS-8i1u3e4w",
    "gender": "Female",
    "date_birth": "1955-12-04",
    "profession": "Programmer Analyst II",
    "fav_color": "Blue",
    "scores": [
      3.33,
      1.1,
      1.18
    ]
  },
  {
    "code": "WB-wfeedqzr",
    "gender": "Female",
    "date_birth": "1997-06-26",
    "profession": "Editor",
    "fav_color": "Blue",
    "scores": [
      1.79,
      1.15,
      2.28
    ]
  },
  {
    "code": "MO-2z6z8w1e",
    "gender": "Male",
    "date_birth": "1992-01-15",
    "profession": "Software Engineer III",
    "fav_color": "Red",
    "scores": [
      0.84,
      1.2,
      2.84
    ]
  }
]